Metadata-Version: 2.1
Name: ncat
Version: 0.1.0
Summary: Python Bindings for NGS Coordinate Conversion and Transformation Tool (NCAT)
Home-page: https://github.com/HaydenElza/ncat-python
Author: Hayden Elza
License: MIT
Download-URL: https://github.com/HaydenElza/ncat-python/archive/v0.1.0.tar.gz
Platform: UNKNOWN
License-File: LICENSE
